gpt_code_ui/__init__.py
gpt_code_ui/main.py
gpt_code_ui/kernel_program/__init__.py
gpt_code_ui/kernel_program/config.py
gpt_code_ui/kernel_program/kernel_manager.py
gpt_code_ui/kernel_program/launch_kernel.py
gpt_code_ui/kernel_program/main.py
gpt_code_ui/kernel_program/utils.py
gpt_code_ui/webapp/__init__.py
gpt_code_ui/webapp/main.py
gpt_code_ui/webapp/static/index.html
gpt_code_ui/webapp/static/assets/assistant.svg
gpt_code_ui/webapp/static/assets/index-0b5a539f.js
gpt_code_ui/webapp/static/assets/index-0d7e582a.css
deepbrainz_interpreter-0.42.41.dist-info/LICENSE
deepbrainz_interpreter-0.42.41.dist-info/METADATA
deepbrainz_interpreter-0.42.41.dist-info/WHEEL
deepbrainz_interpreter-0.42.41.dist-info/entry_points.txt
deepbrainz_interpreter-0.42.41.dist-info/top_level.txt
deepbrainz_interpreter-0.42.41.dist-info/RECORD
