Metadata-Version: 2.1
Name: deepbrainz-interpreter
Version: 0.42.41
Summary: An Open Source version of ChatGPT Code Interpreter
Home-page: UNKNOWN
License: UNKNOWN
Platform: UNKNOWN
License-File: LICENSE
Requires-Dist: Flask (<3,>=2)
Requires-Dist: flask-cors (<4,>=3)
Requires-Dist: ipykernel (<7,>=6)
Requires-Dist: openai (<1,>=0.25)
Requires-Dist: pandas (<2,>=1.3)
Requires-Dist: python-dotenv (<2,>=0.18)
Requires-Dist: requests (<3,>=2)
Requires-Dist: snakemq (<2,>=1)
